publisher/__init__.py
superdesk_publisher-0.1.dist-info/LICENSE
superdesk_publisher-0.1.dist-info/METADATA
superdesk_publisher-0.1.dist-info/WHEEL
superdesk_publisher-0.1.dist-info/top_level.txt
superdesk_publisher-0.1.dist-info/RECORD
