Metadata-Version: 2.1
Name: superdesk-publisher
Version: 0.1
Summary: Superdesk Publisher plugin
Home-page: https://github.com/superdesk/superdesk-publisher
Author: sourcefabric
Author-email: contact@sourcefabric.org
License: GPLv3
Platform: any
